[{"line":2,"elements":[{"line":4,"name":"","description":"","type":"background","keyword":"Background","steps":[{"name":"url baseUrl","result":{"duration":1800900,"status":"passed"},"match":{"location":"karate","arguments":[]},"keyword":"*","line":5},{"name":"header Accept = 'application\/json'","result":{"duration":1726300,"status":"passed"},"match":{"location":"karate","arguments":[]},"keyword":"*","line":6},{"name":"def customerId = 13322","result":{"duration":6156100,"status":"passed"},"match":{"location":"karate","arguments":[]},"keyword":"*","line":7}]},{"start_timestamp":"2025-11-13T02:18:52.022Z","line":9,"name":"Retrieve accounts for a customer","description":"","id":"retrieve-accounts-for-a-customer","type":"scenario","keyword":"Scenario","steps":[{"name":"path 'customers\/' + customerId + '\/accounts'","result":{"duration":2869600,"status":"passed"},"match":{"location":"karate","arguments":[]},"keyword":"Given","line":10},{"name":"method GET","result":{"duration":684146000,"status":"passed"},"match":{"location":"karate","arguments":[]},"keyword":"When","line":11,"doc_string":{"content_type":"","value":"21:18:52.088 request:\n1 > GET http:\/\/parabank.parasoft.com\/parabank\/services\/bank\/customers\/13322\/accounts\n1 > Accept: application\/json\n1 > Host: parabank.parasoft.com\n1 > Connection: Keep-Alive\n1 > User-Agent: Apache-HttpClient\/4.5.13 (Java\/17.0.12)\n1 > Accept-Encoding: gzip,deflate\n\n\n21:18:52.310 request:\n2 > GET http:\/\/parabank.parasoft.com\/parabank\/services\/bank\/customers\/13322\/accounts\n2 > Accept: application\/json\n2 > Host: parabank.parasoft.com\n2 > Connection: Keep-Alive\n2 > User-Agent: Apache-HttpClient\/4.5.13 (Java\/17.0.12)\n2 > Accept-Encoding: gzip,deflate\n\n\n21:18:52.751 response time in milliseconds: 433\n2 < 200\n2 < Date: Thu, 13 Nov 2025 02:18:49 GMT\n2 < Content-Type: application\/json\n2 < Transfer-Encoding: chunked\n2 < Connection: keep-alive\n2 < Server: cloudflare\n2 < cf-cache-status: DYNAMIC\n2 < X-Content-Type-Options: nosniff\n2 < CF-RAY: 99dac7d95941a540-MIA\n[{\"id\":14676,\"customerId\":13322,\"type\":\"CHECKING\",\"balance\":9549.50},{\"id\":14787,\"customerId\":13322,\"type\":\"CHECKING\",\"balance\":-235.00},{\"id\":14898,\"customerId\":13322,\"type\":\"SAVINGS\",\"balance\":666.00},{\"id\":16008,\"customerId\":13322,\"type\":\"LOAN\",\"balance\":-50.00},{\"id\":16119,\"customerId\":13322,\"type\":\"LOAN\",\"balance\":150.00},{\"id\":16230,\"customerId\":13322,\"type\":\"LOAN\",\"balance\":1000.00}]\n\n","line":11}},{"name":"status 200","result":{"duration":28200,"status":"passed"},"match":{"location":"karate","arguments":[]},"keyword":"Then","line":12},{"name":"match response ==","result":{"duration":51075500,"error_message":"match failed: EQUALS\n  $ | not equal | array match failed at index 0 (LIST:LIST)\n  [{\"id\":14676,\"customerId\":13322,\"type\":\"CHECKING\",\"balance\":9549.5},{\"id\":14787,\"customerId\":13322,\"type\":\"CHECKING\",\"balance\":-235.0},{\"id\":14898,\"customerId\":13322,\"type\":\"SAVINGS\",\"balance\":666.0},{\"id\":16008,\"customerId\":13322,\"type\":\"LOAN\",\"balance\":-50.0},{\"id\":16119,\"customerId\":13322,\"type\":\"LOAN\",\"balance\":150.0},{\"id\":16230,\"customerId\":13322,\"type\":\"LOAN\",\"balance\":1000.0}]\n  [{\"id\":14676,\"customerId\":13322,\"type\":\"CHECKING\",\"balance\":9729.5},{\"id\":14787,\"customerId\":13322,\"type\":\"CHECKING\",\"balance\":-471.0},{\"id\":14898,\"customerId\":13322,\"type\":\"SAVINGS\",\"balance\":486.0},{\"id\":16008,\"customerId\":13322,\"type\":\"LOAN\",\"balance\":-50.0},{\"id\":16119,\"customerId\":13322,\"type\":\"LOAN\",\"balance\":150.0},{\"id\":16230,\"customerId\":13322,\"type\":\"LOAN\",\"balance\":1000.0}]\n\n    $[0] | not equal | match failed for name: 'balance' (MAP:MAP)\n    {\"id\":14676,\"customerId\":13322,\"type\":\"CHECKING\",\"balance\":9549.5}\n    {\"id\":14676,\"customerId\":13322,\"type\":\"CHECKING\",\"balance\":9729.5}\n\n      $[0].balance | not equal (NUMBER:NUMBER)\n      9549.5\n      9729.5\n\nclasspath:org\/udea\/parabank\/GetAccounts.feature:13","status":"failed"},"match":{"location":"karate","arguments":[]},"keyword":"And","line":13,"doc_string":{"content_type":"","value":"[\n  {\n    \"id\": 14676,\n    \"customerId\": #(customerId),\n    \"type\": \"CHECKING\",\n    \"balance\": 9729.50\n  },\n  {\n    \"id\": 14787,\n    \"customerId\": #(customerId),\n    \"type\": \"CHECKING\",\n    \"balance\": -471.00\n  },\n  {\n    \"id\": 14898,\n    \"customerId\": #(customerId),\n    \"type\": \"SAVINGS\",\n    \"balance\": 486.00\n  },\n  {\n    \"id\": 16008,\n    \"customerId\": #(customerId),\n    \"type\": \"LOAN\",\n    \"balance\": -50.00\n  },\n  {\n    \"id\": 16119,\n    \"customerId\": #(customerId),\n    \"type\": \"LOAN\",\n    \"balance\": 150.00\n  },\n  {\n    \"id\": 16230,\n    \"customerId\": #(customerId),\n    \"type\": \"LOAN\",\n    \"balance\": 1000.00\n  }\n]21:18:52.808 classpath:org\/udea\/parabank\/GetAccounts.feature:13\nAnd match response ==\n\"\"\"\n[\n  {\n    \"id\": 14676,\n    \"customerId\": #(customerId),\n    \"type\": \"CHECKING\",\n    \"balance\": 9729.50\n  },\n  {\n    \"id\": 14787,\n    \"customerId\": #(customerId),\n    \"type\": \"CHECKING\",\n    \"balance\": -471.00\n  },\n  {\n    \"id\": 14898,\n    \"customerId\": #(customerId),\n    \"type\": \"SAVINGS\",\n    \"balance\": 486.00\n  },\n  {\n    \"id\": 16008,\n    \"customerId\": #(customerId),\n    \"type\": \"LOAN\",\n    \"balance\": -50.00\n  },\n  {\n    \"id\": 16119,\n    \"customerId\": #(customerId),\n    \"type\": \"LOAN\",\n    \"balance\": 150.00\n  },\n  {\n    \"id\": 16230,\n    \"customerId\": #(customerId),\n    \"type\": \"LOAN\",\n    \"balance\": 1000.00\n  }\n]\n\"\"\"\nmatch failed: EQUALS\n  $ | not equal | array match failed at index 0 (LIST:LIST)\n  [{\"id\":14676,\"customerId\":13322,\"type\":\"CHECKING\",\"balance\":9549.5},{\"id\":14787,\"customerId\":13322,\"type\":\"CHECKING\",\"balance\":-235.0},{\"id\":14898,\"customerId\":13322,\"type\":\"SAVINGS\",\"balance\":666.0},{\"id\":16008,\"customerId\":13322,\"type\":\"LOAN\",\"balance\":-50.0},{\"id\":16119,\"customerId\":13322,\"type\":\"LOAN\",\"balance\":150.0},{\"id\":16230,\"customerId\":13322,\"type\":\"LOAN\",\"balance\":1000.0}]\n  [{\"id\":14676,\"customerId\":13322,\"type\":\"CHECKING\",\"balance\":9729.5},{\"id\":14787,\"customerId\":13322,\"type\":\"CHECKING\",\"balance\":-471.0},{\"id\":14898,\"customerId\":13322,\"type\":\"SAVINGS\",\"balance\":486.0},{\"id\":16008,\"customerId\":13322,\"type\":\"LOAN\",\"balance\":-50.0},{\"id\":16119,\"customerId\":13322,\"type\":\"LOAN\",\"balance\":150.0},{\"id\":16230,\"customerId\":13322,\"type\":\"LOAN\",\"balance\":1000.0}]\n\n    $[0] | not equal | match failed for name: 'balance' (MAP:MAP)\n    {\"id\":14676,\"customerId\":13322,\"type\":\"CHECKING\",\"balance\":9549.5}\n    {\"id\":14676,\"customerId\":13322,\"type\":\"CHECKING\",\"balance\":9729.5}\n\n      $[0].balance | not equal (NUMBER:NUMBER)\n      9549.5\n      9729.5\n\nclasspath:org\/udea\/parabank\/GetAccounts.feature:13\n","line":13}}],"tags":[{"name":"@parabank_get_accounts","line":1}]},{"line":4,"name":"","description":"","type":"background","keyword":"Background","steps":[{"name":"url baseUrl","result":{"duration":300400,"status":"passed"},"match":{"location":"karate","arguments":[]},"keyword":"*","line":5},{"name":"header Accept = 'application\/json'","result":{"duration":851300,"status":"passed"},"match":{"location":"karate","arguments":[]},"keyword":"*","line":6},{"name":"def customerId = 13322","result":{"duration":1437800,"status":"passed"},"match":{"location":"karate","arguments":[]},"keyword":"*","line":7}]},{"start_timestamp":"2025-11-13T02:18:52.842Z","line":55,"name":"Failed Retrieve accounts for a customer","description":"","id":"failed-retrieve-accounts-for-a-customer","type":"scenario","keyword":"Scenario","steps":[{"name":"def fakeCustomerId = 999990","result":{"duration":1217800,"status":"passed"},"match":{"location":"karate","arguments":[]},"keyword":"Given","line":56},{"name":"path 'customers\/' + fakeCustomerId + '\/accounts'","result":{"duration":1687200,"status":"passed"},"match":{"location":"karate","arguments":[]},"keyword":"And","line":57},{"name":"method GET","result":{"duration":810829200,"status":"passed"},"match":{"location":"karate","arguments":[]},"keyword":"When","line":58,"doc_string":{"content_type":"","value":"21:18:52.857 request:\n1 > GET http:\/\/parabank.parasoft.com\/parabank\/services\/bank\/customers\/999990\/accounts\n1 > Accept: application\/json\n1 > Host: parabank.parasoft.com\n1 > Connection: Keep-Alive\n1 > User-Agent: Apache-HttpClient\/4.5.13 (Java\/17.0.12)\n1 > Accept-Encoding: gzip,deflate\n\n\n21:18:53.180 request:\n2 > GET http:\/\/parabank.parasoft.com\/parabank\/services\/bank\/customers\/999990\/accounts\n2 > Accept: application\/json\n2 > Host: parabank.parasoft.com\n2 > Connection: Keep-Alive\n2 > User-Agent: Apache-HttpClient\/4.5.13 (Java\/17.0.12)\n2 > Accept-Encoding: gzip,deflate\n\n\n21:18:53.664 response time in milliseconds: 483\n2 < 400\n2 < Date: Thu, 13 Nov 2025 02:18:50 GMT\n2 < Content-Type: text\/plain;charset=UTF-8\n2 < Content-Length: 31\n2 < Connection: keep-alive\n2 < Server: cloudflare\n2 < cf-cache-status: DYNAMIC\n2 < X-Content-Type-Options: nosniff\n2 < CF-RAY: 99dac7de3e719d81-MIA\nCould not find customer #999990\n\n","line":58}},{"name":"status 400","result":{"duration":23800,"status":"passed"},"match":{"location":"karate","arguments":[]},"keyword":"Then","line":59},{"name":"match response == \"Could not find customer #\" + fakeCustomerId","result":{"duration":2107700,"status":"passed"},"match":{"location":"karate","arguments":[]},"keyword":"And","line":60}],"tags":[{"name":"@parabank_get_accounts","line":1}]}],"name":"org\/udea\/parabank\/GetAccounts.feature","description":"Get user accounts from Parabank","id":"get-user-accounts-from-parabank","keyword":"Feature","uri":"org\/udea\/parabank\/GetAccounts.feature","tags":[{"name":"@parabank_get_accounts","line":1}]}]